buildbot_matrix/__init__.py
buildbot_matrix/reporter.py
buildbot_matrix-0.0.5.dist-info/LICENSE
buildbot_matrix-0.0.5.dist-info/METADATA
buildbot_matrix-0.0.5.dist-info/WHEEL
buildbot_matrix-0.0.5.dist-info/entry_points.txt
buildbot_matrix-0.0.5.dist-info/top_level.txt
buildbot_matrix-0.0.5.dist-info/RECORD
