Metadata-Version: 2.1
Name: buildbot-matrix
Version: 0.0.5
Summary: buildbot plugin for using matrix for notifications
Home-page: https://github.com/HayWo/buildbot-matrix
Author: HayWo
Author-email: opensource@nct08.de
License: UNKNOWN
Platform: UNKNOWN
Classifier: Development Status :: 5 - Production/Stable
Classifier: Programming Language :: Python :: 3
Classifier: Environment :: Plugins
Classifier: Intended Audience :: Developers
Classifier: License :: OSI Approved :: MIT License
Classifier: Operating System :: Microsoft :: Windows
Classifier: Operating System :: MacOS
Classifier: Operating System :: POSIX :: Linux
Classifier: Topic :: Software Development :: Build Tools
Requires: buildbot (>=2.0.0)
Requires-Python: >=3.6
